{
  "schema": "vela.event.v0.1",
  "id": "vev_c53f55541be51b5c",
  "kind": "assertion.reinterpreted_causal",
  "target": {
    "type": "finding",
    "id": "vf_f4651ca741de35c7"
  },
  "actor": {
    "id": "reviewer:will-blair",
    "type": "human"
  },
  "timestamp": "2026-04-27T23:26:52.666197+00:00",
  "reason": "v0.40 initial classification (heuristic over assertion text + evidence type + conditions)",
  "before_hash": "sha256:8531ada1aef03be33ffb4b01a15ced9294e9f0976e69820c134f6a2ab90eaa9e",
  "after_hash": "sha256:dc06a3bba002b12e5053c5308f706c4e384469808c93cf49d26348917f5472d5",
  "payload": {
    "after": {
      "claim": "correlation",
      "grade": "quasi_experimental"
    },
    "before": {
      "claim": null,
      "grade": null
    },
    "proposal_id": "vpr_9c4ac09fd706c985"
  },
  "caveats": []
}