{
  "schema": "vela.event.v0.1",
  "id": "vev_b6dd1d4f437eafef",
  "kind": "assertion.reinterpreted_causal",
  "target": {
    "type": "finding",
    "id": "vf_f4445212405c2730"
  },
  "actor": {
    "id": "reviewer:will-blair",
    "type": "human"
  },
  "timestamp": "2026-04-27T23:26:52.598076+00:00",
  "reason": "v0.40 initial classification (heuristic over assertion text + evidence type + conditions)",
  "before_hash": "sha256:18c50a4f7de5889aadf34460108b2f7d34b07d69a361ef296e4d0957d6a7a8cf",
  "after_hash": "sha256:27c6f3f3887e058310a5ac0fd55635880171be96946cdf21efe102682966c90c",
  "payload": {
    "after": {
      "claim": "correlation",
      "grade": "quasi_experimental"
    },
    "before": {
      "claim": null,
      "grade": null
    },
    "proposal_id": "vpr_30698294a09971e4"
  },
  "caveats": []
}