{
  "schema": "vela.event.v0.1",
  "id": "vev_b9d20f95640e1ab7",
  "kind": "assertion.reinterpreted_causal",
  "target": {
    "type": "finding",
    "id": "vf_47ebdf11b9b45680"
  },
  "actor": {
    "id": "reviewer:will-blair",
    "type": "human"
  },
  "timestamp": "2026-04-27T23:26:48.289811+00:00",
  "reason": "v0.40 initial classification (heuristic over assertion text + evidence type + conditions)",
  "before_hash": "sha256:f9cf944224a7a7fc8430ee7c2079a7ef278f8ff1a50708da2481486ced5a0071",
  "after_hash": "sha256:a4a3798c32ca366dcc9b012a563df973a62584fbfd20f01c0eb526fda554547f",
  "payload": {
    "after": {
      "claim": "mediation",
      "grade": "quasi_experimental"
    },
    "before": {
      "claim": null,
      "grade": null
    },
    "proposal_id": "vpr_cfa29e7517f144dc"
  },
  "caveats": []
}